async_hvac/__init__.py
async_hvac/aws_utils.py
async_hvac/exceptions.py
async_hvac/version
async_hvac/tests/__init__.py
async_hvac/tests/test_approle_routes.py
async_hvac/tests/test_auth_methods.py
async_hvac/tests/test_aws_ec2_methods.py
async_hvac/tests/test_aws_iam_methods.py
async_hvac/tests/test_client.py
async_hvac/tests/test_gcp_methods.py
async_hvac/tests/test_integration.py
async_hvac/tests/test_kubernetes_methods.py
async_hvac/tests/util.py
async_hvac/v1/__init__.py
vtb_async_hvac-0.6.2.dist-info/LICENSE.txt
vtb_async_hvac-0.6.2.dist-info/METADATA
vtb_async_hvac-0.6.2.dist-info/WHEEL
vtb_async_hvac-0.6.2.dist-info/top_level.txt
vtb_async_hvac-0.6.2.dist-info/RECORD
